{"metadata": [{"year": "2013", "description": "From the mastermind behind Neotopia and Courageous Princess comes this spectacular steampunk take on a classic fairy tale! In a far-off kingdom, the queen sends her armies of steam-powered juggernauts to successful conquest, all while she and her subordinate lords pass the wartime expenses on to the peasants. Her daughter, Princess White, protests to no avail. The commoners' only hope is the daring raider Lone Fox, but on his latest assault the vigilante is ambushed!", "type": "comicSeries", "publisher": "Antarctic Press", "name": "Steampunk Snow White"}]}