{"metadata": [{"publisher": "Kodansha Comics Digital-First!", "year": "2015", "type": "comicSeries", "description": "Subscribe to this series and get chapters automatically delivered to your library when they're released. You won\u2019t get any prior issues, backlist items, or collections. New chapters only.\n\nBessatsu Shonen Magazine's hugely popular story of survival and suspense moves to Weekly Shonen Magazine as a completely brand-new series! With the appearance of a strange daruma doll, ordinary life crumbles away in an instant. Even so, live on. Survive. This is the story of the \"life\" bestowed upon all those who have wished to die. Are you beef or chicken? Live, that's the only rule.", "name": "As The Gods Will: The Second Series"}]}