{"metadata": [{"year": "2017", "description": "In this graphic novel by a cult cartoonist, orphaned siblings grapple with survival, sex, and mortality in a stylized world. Zegas details the surreal urban adventures of the recently orphaned Zegas siblings. The ambitious Emily and her moody brother, Boston, are young adults who confront their new relationship dynamic in the face of a family tragedy that never gets talked about.", "type": "comicSeries", "publisher": "Fantagraphics", "name": "Zegas"}]}