{"metadata": [{"name": "Yuga", "year": "2018", "description": "In the wake of the Great War, a truce was born between the Asuras and the Devas. They left their creation, humanity, behind on earth, protected by the Guardians, as they sought new homes. For hundreds of years, they maintained this peace. But it did not last.  A young Asura, curious of earth\u2019s legend traveled to the planet, disguised as a tiger. He came upon King Toman\u2019s kingdom and was killed for posing a threat to its people. The Guardians were nowhere to be found. The Asura\u2019s father, Prince Varrik, took revenge. He slaughtered the King and Queen and kidnapped their newborn son.\n", "publisher": "AAM-Markosia", "type": "comicSeries"}]}