{"metadata": [{"year": "2016", "description": "When Esteban, a young Native American boy of just 12-years-old, presents himself to the captain of the Leviathan for the post of 'harpooner', he's the laughing stock of the whole crew. But when the captain finds out that Esteban is the son of Suzanna of the Tehuelches tribe, he decides to take him on... as ship's boy. Despite his lowly post, this is Esteban's chance to discover the sailor's life, with all its hardship and its happiness, and maybe even a chance to prove what he's made of!", "type": "comicSeries", "publisher": "Europe Comics", "name": "Esteban"}]}