{"metadata": [{"year": "2010", "description": "The temperature rises to a boiling point at the prison island of San Tiburon as 185 superpowered prisoners begin to riot against their captors. A murderous psychopath takes a hostage into the jungle with vengeful ambitions, a superhero delivers his nemesis into the waiting hands of prison officials, a conspiracy is revealed, and Captain Jason Brody finds there are consequences for every action, no matter how noble the intentions.", "type": "comicSeries", "publisher": "Arcana Comics", "name": "Corrective Measures Vol 2"}]}