{"metadata": [{"year": "2018", "description": "From the Eisner and Harvey award-winning creator of SNARKED and writer of the acclaimed comic series D4VE comes this humorous, absurd adventure tale about a family on the run.\n\nDaggum Criminy's peaceful life is suddenly interrupted as pirates invade his island, casting Criminy's family out as refugees into the wild unknown in search of a new home. Soon, the Criminys find themselves hopping from one strange locale to another, each with their own bizarre environment, people, and challenges; putting Daggum and fam in constant peril as they search for a new peaceful place to call home.\n", "type": "comicSeries", "publisher": "Dark Horse", "name": "Criminy"}]}