{"metadata": [{"year": "2019", "description": "Sent on a covert mission without the rest of her team, Spartan Linda-058's skills in infiltration and marksmanship are called upon to end the threat posed by a wanted scientist on a distant planet. With only an ONI AI at her side, Linda must fight through both the dregs of the Covenant and the hostility of a lost human settlement to stop the rogue scientist in his tracks. Collects issues #1-#4 of the series.\n", "type": "comicSeries", "publisher": "Dark Horse", "name": "Halo: Lone Wolf"}]}