{"metadata": [{"year": "2016", "description": "Double-sized debut spectacular! This 48-page special includes all Kings Road chapters from Dark Horse Presents by Peter Hogan and Phil Winsladeand an additional issues worth of story drawn by the new Kings Road art team! Artist Staz Johnson (Judge Dredd) and colorist Douglas A. Sirois (The 7th Sword) join Hogan to continue this tale of a family on the run from magical, other-dimensional monsters. Value-priced double issue! 48 pages for $3.99! Clearly one of the best original creations to come out of Dark Horse in recent memory.\u009dComics Bulletin", "type": "comicSeries", "publisher": "Dark Horse", "name": "King's Road"}]}