{"metadata": [{"year": "2019", "description": "Planet Earth: 500,000 years in the future. Humans have been extinct for millennia. Two scientists, Robert and June, have been orbiting the Earth, waiting for the planet to become habitable once more. With the help of a team of robots, they plan to start over from scratch: a new Adam and Eve who won't make the same mistakes as their ancestors. But first Robert has to find June, who seems to have landed somewhere else in this vast jungle\u2014their Eden\u2014full of grotesque creatures and strange primates...\n", "type": "comicSeries", "publisher": "Europe Comics", "name": "Human"}]}