{"metadata": [{"year": "2019", "description": "Nouvelle \u00e9dition mise \u00e0 jour et enrichie de nouvelles photos.\nLa Cit\u00e9 des Doges n\u2019a pas une, mais plusieurs histoires, depuis la cit\u00e9 lacustre, o\u00f9 venaient se r\u00e9fugier les V\u00e9n\u00e8tes fuyant les invasions barbares jusqu\u2019\u00e0 la construction d\u00e9finitive de l\u2019Arsenal, o\u00f9 les artisans firent na\u00eetre l\u2019invincibilit\u00e9 de cette r\u00e9publique maritime. Une cit\u00e9 unique au monde, cosmopolite, centre commercial de la M\u00e9diterran\u00e9e, vers o\u00f9 convergeaient d\u2019immenses richesses venues de l\u2019ensemble du monde connu. Il fallait bien toute la science de Jacques Martin et le talent graphique d\u2019Enrico Sallustio, V\u00e9nitien d\u2019origine, pour faire revivre les hautes heures d\u2019une cit\u00e9 fabuleuse qui continue \u00e0 cacher ses secrets \u00e0 l\u2019ombre du Lido et du palais des Doges, non loin du pont des Soupirs \u2013 le tout sous le regard vigilant de l\u2019ap\u00f4tre Marc, dont les restes furent emmen\u00e9s d\u2019\u00c9gypte et sans lequel la basilique, qui porte son nom, ne serait pas tout \u00e0 fait ce qu\u2019elle est devenue. En compagnie de Jhen, le b\u00e2tisseur de cath\u00e9drales, un voyage dans le temps qui est aussi un voyage au pays des merveilles.", "type": "comicSeries", "publisher": "Casterman", "name": "Les Voyages de Jhen"}]}