{"metadata": [{"year": "2016", "description": "Astrid and Dave are teenagers stuck in a dead-end suburban town living uneventful lives - until Astrid gets a visit from her childhood imaginary friends, who tell her something big is about to happen. Are they real or is she crazy? Life is about to get a lot more interesting for the pair - interesting and very, very dangerous. From the co-creator of PHONOGRAM comes this tale of magic, mystery and underage drinking.", "type": "comicSeries", "publisher": "Image", "name": "Suburban Glamour, Vol. 1"}]}