{"metadata": [{"year": "2013", "description": "Enter the retrofuturistic world of Mercy St. Clair, a talented and troubled bounty hunter navigating a society steeped in extreme violence on her journey of growth and self-discovery. \n\nOver 60 pages of brand-new color material! \n\nRon Randall's sci-fi adventure opus! \n\nMercy is on her emotional journey... adventures filled with strange technologies and creatures, far-flung politics, and lots and lots of action.\",io9", "type": "comicSeries", "publisher": "Dark Horse", "name": "Trekker"}]}