{"metadata": [{"year": "2015", "description": "Alice, jeune blonde fra\u00eeche et s\u00e9duisante se cherche dans une ville banale de l\u2019Am\u00e9rique des ann\u00e9es 90. Elle cherche l\u2019amour, elle cherche un sens \u00e0 sa vie. Isadora, la clocharde, alcoolique\u2026 qui se cache derri\u00e8re cette fa\u00e7ade, y avait-il une femme avant l\u2019\u00e9pave ?Billie, est l\u2019amie d\u2019Alice. Elle ne va plus au cours de danse. Billie est noire. Billie est amoureuse d\u2019un blanc. Barack Obama n\u2019est pas encore pr\u00e9sident. Dwight aurait bien pu s\u2019appeler Kurt. Artiste dans l\u2019\u00e2me, il dessine. Il aime dessiner Alice\u2026", "type": "comicSeries", "publisher": "Casterman", "name": "Comment naissent les araign\u00e9es"}]}