{"metadata": [{"year": "2004", "description": "THE CONCEPT: Detective Kane returns to active duty with the New Eden Police Dept. following a six-month suspension after he shot and killed his partner Dennis Harvey. His fellow police officers give Kane a welcome back gift: a couple of bullets with his name engraved on them.\nTHIS ISSUE: Partnered with a new detective, Kate Felix, Kane quickly learns nothing has changed in the city of New Eden. In his first two days back, Kane has to deal with a siege, a kidnapping and a bomb attack. And then there's the Crime Boss of New Eden, Oscar Darke... Collects KANE #1-4, originally published by Dancing Elephant Press. ", "type": "comicSeries", "publisher": "Image", "name": "Kane"}]}