{"metadata": [{"year": "2016", "description": "This action-packed original graphic novel contains all-new Halo\u00ae stories from some of the comic industry\u2019s best\u2014Jonathan Wayshak, Eric Nguyen, Alex Irvine, Vasilis Lolos, Kody Chamberlain, Dave Crosland, John Jackson Miller, Jonathan Goff, Simon Roy, and Halo: Escalation writer Duffy Boudreau\u2014as well as 343 Industries\u2019 own franchise development director, Frank O\u2019Connor, and franchise producer, Tyler Jeffers!\n\n* This action-packed anthology is essential reading for all Halo fans!\n\n* Standalone OGN is also great for new readers!\n", "type": "comicSeries", "publisher": "Dark Horse", "name": "Halo: Tales from Slipspace"}]}