{"metadata": [{"year": "2019", "description": "In the tradition of Conan the Barbarian. Three young men embark on a quest to find and kill Khor, a despotic warrior/wizard of the land who has a track record of destroying and annihilating all who have attempted to oppose him. Along their journey the young men will face various obstacles and challenges, and seek help in a monastery where they are given guidance as to where they can obtain the materials needed to face and possibly defeat Khor. However their dangerous adventure is not so smooth and clear cut as the young men must first defeat Khor's trusted lieutenant, and Khor's military forces, before coming face to face with Khor himself!", "type": "comicSeries", "publisher": "Caliber Comics", "name": "Khor's Land"}]}