{"metadata": [{"year": "2017", "description": "\u00c9branl\u00e9 par un incendie qui aurait pu lui co\u00fbter la vie, le narrateur de cette histoire ressent le besoin de renouer avec son propre pass\u00e9, mat\u00e9rialis\u00e9 par une s\u00e9rie d\u2019albums photos qui r\u00e9capitulent une bonne part de son existence \u2013 \u00e0 commencer par la m\u00e9moire de son p\u00e8re trop t\u00f4t disparu. Ainsi d\u00e9bute une \u00e9trange p\u00e9riode qui, huit jours durant, conduit cet homme solitaire et secret sur le chemin d\u2019une profonde introspection. Avec la complicit\u00e9 de son jeune neveu Anthony, qui lui est profond\u00e9ment attach\u00e9, il entreprend une sorte de p\u00e8lerinage impromptu au c\u0153ur de ses racines familiales, habit\u00e9 par le sentiment du temps qui passe et la conscience aigu\u00eb de la fugacit\u00e9 des \u00eatres et des choses. Ce voyage \u00e0 rebours de plus de trente ans, \u00e0 la fois g\u00e9ographique et int\u00e9rieur, lui permettra, gr\u00e2ce \u00e0 une lettre miraculeusement retrouv\u00e9e, de red\u00e9couvrir la profondeur de son attachement pour son p\u00e8re et de se confronter enfin \u00e0 un d\u00e9sir de paternit\u00e9 longtemps refoul\u00e9. Avec pudeur, distance et une tr\u00e8s discr\u00e8te touche d\u2019humour, Didier Tronchet transpose en bande dessin\u00e9e, en noir et blanc et sur un format de longue haleine, son propre roman \u00e9ponyme paru en 2011 chez Flammarion. Une mani\u00e8re de d\u00e9voiler un registre sensible et intimiste qu\u2019on ne lui connaissait pas en bande dessin\u00e9e, et une r\u00e9flexion touchante sur les ressorts de la filiation.", "type": "comicSeries", "publisher": "Casterman", "name": "Le fils du Y\u00e9ti"}]}