{"metadata": [{"publisher": "Kodansha Comics", "year": "2020", "type": "comicSeries", "description": "\"In this new spinoff of the hit manga, a newbie Red Blood Cell is one of 37 trillion working to keep this body running. But something\u2019s wrong! Stress hormones keep yelling at him to go faster. The blood vessels are crusted over with cholesterol. Ulcers, fatty liver, trouble (ahem) downstairs\u2026 It\u2019s hard for a cell to keep working when every day is a CODE BLACK!\n\nTHE CONTENT OF ADULTS\n\nThere are trillions of cells in the human body, and they all have to work hard to keep that body alive. But what if that body isn\u2019t taking great care of itself? What if that body smokes too much? Or drinks too much? What if that body forgets to use protection? Why, it might find itself with all manner of dysfunction, and who\u2019s going to have to pick up the pieces? It turns out the same immune cells that fight off the common cold also have to deal with troubles of a distinctly more adult nature\u2026\"", "name": "Cells at Work! CODE BLACK"}]}