{"metadata": [{"publisher": "Kodansha Comics Digital-First!", "year": "2020", "type": "comicSeries", "description": "From Tsuyoshi Yasuda, the author of Over Drive and Furimuku Na Kimi Wa, comes the most exciting soccer manga in the world! During his last spring break before starting high school, Tsukushi Tsukamoto meets Jin Kazama, who invites him to a pick-up soccer game. Their chance meeting, and his first-ever experience with soccer, move kind-hearted, timid Tsukushi to enroll in his new high school's soccer club, which is among the strongest in all of Japan. Unbeknownst to the rest of the world, there's something amazing hidden inside Tsukushi's heart...and through the trials and tribulations of his time in the soccer club, it's beginning to blossom!", "name": "DAYS"}]}