{"metadata": [{"year": "2011", "description": "IDW's Infestation event continues here in this two-part Ghostbusters tale! Thanks to a plague of poltergeists that resist long-term storage in the containment grid, the Ghostbusters are dealing with a surplus of work... and their job is only going to get harder when Britt's zombies try to take a nibble out of the Big Apple! Written by Erik Burnham (The A-Team: War Stories) and illustrated by Kyle Hotz (Marvel Zombies).\n", "type": "comicSeries", "publisher": "IDW", "name": "Ghostbusters: Infestation"}]}